ln_pluggy/__init__.py
ln_pluggy/_callers.py
ln_pluggy/_hooks.py
ln_pluggy/_manager.py
ln_pluggy/_result.py
ln_pluggy/_tracing.py
ln_pluggy/_version.py
ln_pluggy/_warnings.py
ln_pluggy/py.typed
ln_pluggy-1.4.0.240207.dist-info/LICENSE
ln_pluggy-1.4.0.240207.dist-info/METADATA
ln_pluggy-1.4.0.240207.dist-info/WHEEL
ln_pluggy-1.4.0.240207.dist-info/top_level.txt
ln_pluggy-1.4.0.240207.dist-info/RECORD
